micooc/__init__.py
micooc/micooc.py
micooc-0.1.4.dist-info/LICENSE
micooc-0.1.4.dist-info/METADATA
micooc-0.1.4.dist-info/WHEEL
micooc-0.1.4.dist-info/top_level.txt
micooc-0.1.4.dist-info/RECORD
