Metadata-Version: 2.1
Name: micooc
Version: 0.1.4
Summary: Micoo client for python
Home-page: https://github.com/Mikuu/Micoo
Author: ariman
Author-email: biaofu@thoughtworks.com
License: UNKNOWN
Platform: UNKNOWN
Classifier: Programming Language :: Python :: 3
Classifier: License :: OSI Approved :: MIT License
Classifier: Operating System :: OS Independent
Requires-Python: >=3.6
